{"id": "o9ktH9fM", "meta": {"nbPlayers": 106, "duels": [], "isFinished": true, "podium": [{"name": "papasi", "title": "IM", "flair": "people.man-pilot-light-skin-tone", "patron": true, "patronColor": 10, "rank": 1, "rating": 2441, "score": 55, "nb": {"game": 26, "berserk": 2, "win": 18}, "performance": 2553}, {"name": "fatalispm", "rank": 2, "rating": 2413, "score": 50, "nb": {"game": 18, "berserk": 9, "win": 13}, "performance": 2576}, {"name": "PchelkinVK", "title": "CM", "flair": "nature.honeybee", "patron": true, "patronColor": 2, "rank": 3, "rating": 2475, "score": 43, "nb": {"game": 25, "berserk": 6, "win": 16}, "performance": 2477}], "pairingsClosed": true, "stats": {"games": 499, "moves": 42524, "whiteWins": 251, "blackWins": 213, "draws": 35, "berserks": 81, "averageRating": 2275}, "standing": {"page": 1, "players": [{"name": "papasi", "title": "IM", "flair": "people.man-pilot-light-skin-tone", "patron": true, "patronColor": 10, "rank": 1, "rating": 2441, "score": 55, "sheet": {"scores": "02444220422044222422003022"}}, {"name": "fatalispm", "rank": 2, "rating": 2413, "score": 50, "sheet": {"scores": "300243200454454433"}}, {"name": "PchelkinVK", "title": "CM", "flair": "nature.honeybee", "patron": true, "patronColor": 2, "rank": 3, "rating": 2475, "score": 43, "sheet": {"scores": "3210305320200204220220422", "fire": true}}, {"name": "SunoftheBeach", "rank": 4, "rating": 2426, "score": 39, "sheet": {"scores": "24220220444422020210000"}}, {"name": "Loay23", "title": "IM", "flair": "nature.full-moon", "rank": 5, "rating": 2364, "score": 36, "sheet": {"scores": "0022020020224444422"}}, {"name": "Kinzya1", "rank": 6, "rating": 2325, "score": 35, "sheet": {"scores": "44442201222002020022", "fire": true}}, {"name": "DOOGE228", "rank": 7, "rating": 2335, "score": 32, "sheet": {"scores": "202220200204422020020202"}}, {"name": "Strelok2222", "title": "FM", "rank": 8, "rating": 2360, "score": 32, "sheet": {"scores": "0313023023000220002230022"}}, {"name": "Damianlamy", "rank": 9, "rating": 2262, "score": 30, "sheet": {"scores": "200002200022020444230100"}}, {"name": "DrGodstein", "rank": 10, "rating": 2295, "score": 28, "sheet": {"scores": "0004222442201001022"}}]}, "id": "o9ktH9fM", "createdBy": "lichess", "startsAt": "2019-02-16T17:00:00Z", "system": "arena", "fullName": "Elite SuperBlitz Arena", "minutes": 120, "perf": {"key": "blitz", "name": "Blitz", "icon": ")"}, "clock": {"limit": 180, "increment": 0}, "variant": "standard", "rated": true, "berserkable": true, "verdicts": {"list": [{"condition": "\u2265 20 Blitz rated games", "verdict": "ok"}, {"condition": "Rated \u2265 2200 in Blitz", "verdict": "ok"}], "accepted": true}, "schedule": {"freq": "weekend", "speed": "superBlitz"}, "minRating": {"rating": 2200}, "minRatedGames": {"nb": 20}}, "results": [{"rank": 1, "score": 55, "rating": 2441, "username": "papasi", "title": "IM", "flair": "people.man-pilot-light-skin-tone", "patronColor": 10, "performance": 2553}, {"rank": 2, "score": 50, "rating": 2413, "username": "fatalispm", "performance": 2576}, {"rank": 3, "score": 43, "rating": 2475, "username": "PchelkinVK", "title": "CM", "flair": "nature.honeybee", "patronColor": 2, "performance": 2477}, {"rank": 4, "score": 39, "rating": 2426, "username": "SunoftheBeach", "performance": 2418}, {"rank": 5, "score": 36, "rating": 2364, "username": "Loay23", "title": "IM", "flair": "nature.full-moon", "performance": 2506}, {"rank": 6, "score": 35, "rating": 2325, "username": "Kinzya1", "performance": 2428}, {"rank": 7, "score": 32, "rating": 2335, "username": "DOOGE228", "performance": 2378}, {"rank": 8, "score": 32, "rating": 2360, "username": "Strelok2222", "title": "FM", "performance": 2302}, {"rank": 9, "score": 30, "rating": 2262, "username": "Damianlamy", "performance": 2267}, {"rank": 10, "score": 28, "rating": 2295, "username": "DrGodstein", "performance": 2342}, {"rank": 11, "score": 27, "rating": 2466, "username": "Meldney", "performance": 2543}, {"rank": 12, "score": 27, "rating": 2359, "username": "sapber", "performance": 2305}, {"rank": 13, "score": 27, "rating": 2248, "username": "Niper13", "performance": 2236}, {"rank": 14, "score": 26, "rating": 2288, "username": "TausendjahrigeAdler", "performance": 2310}, {"rank": 15, "score": 24, "rating": 2382, "username": "zakramnika", "performance": 2445}, {"rank": 16, "score": 23, "rating": 2355, "username": "Coup_de_Grace", "performance": 2471}, {"rank": 17, "score": 23, "rating": 2334, "username": "PJatoba", "title": "FM", "performance": 2365}, {"rank": 18, "score": 22, "rating": 2223, "username": "Shilichkov", "title": "IM", "performance": 2586}, {"rank": 19, "score": 22, "rating": 2291, "username": "StepanOsinovsky", "title": "FM", "performance": 2330}, {"rank": 20, "score": 22, "rating": 2333, "username": "Chaozu", "title": "IM", "performance": 2316}, {"rank": 21, "score": 22, "rating": 2151, "username": "HrvojeZagreb", "title": "CM", "patronColor": 10, "performance": 2295}, {"rank": 22, "score": 22, "rating": 2226, "username": "Zairona", "performance": 2225}, {"rank": 23, "score": 21, "rating": 2333, "username": "tapkus", "performance": 2351}, {"rank": 24, "score": 20, "rating": 2315, "username": "JorgeHerreraQuintero", "performance": 2549}, {"rank": 25, "score": 20, "rating": 2322, "username": "Grandi66", "performance": 2355}, {"rank": 26, "score": 20, "rating": 2272, "username": "oldmisio", "performance": 2276}, {"rank": 27, "score": 20, "rating": 2244, "username": "smashinglad", "performance": 2271}, {"rank": 28, "score": 20, "rating": 2239, "username": "Gagik-navak", "performance": 2181}, {"rank": 29, "score": 19, "rating": 2412, "username": "Sergey_Naboka", "title": "FM", "performance": 2492}, {"rank": 30, "score": 19, "rating": 2297, "username": "Win-all-you", "performance": 2291}, {"rank": 31, "score": 18, "rating": 2323, "username": "ExtremeTactic", "title": "FM", "performance": 2471}, {"rank": 32, "score": 17, "rating": 2327, "username": "ShaSerOl", "performance": 2240}, {"rank": 33, "score": 16, "rating": 2415, "username": "gefuehlter_FM", "performance": 2571}, {"rank": 34, "score": 16, "rating": 2345, "username": "Grammnik", "title": "FM", "flair": "people.hand-with-fingers-splayed", "performance": 2435}, {"rank": 35, "score": 16, "rating": 2382, "username": "uhlmannfan", "title": "FM", "performance": 2426}, {"rank": 36, "score": 15, "rating": 2240, "username": "adrinalin", "performance": 2336}, {"rank": 37, "score": 14, "rating": 2458, "username": "Pliukha_M", "performance": 2339}, {"rank": 38, "score": 14, "rating": 2245, "username": "berto777", "performance": 2168}, {"rank": 39, "score": 14, "rating": 2182, "username": "jigsaw123", "performance": 2073}, {"rank": 40, "score": 13, "rating": 2240, "username": "Belsazar", "patronColor": 10, "performance": 2240}, {"rank": 41, "score": 12, "rating": 2319, "username": "jesselroy99", "title": "FM", "flair": "smileys.face-in-clouds", "performance": 2497}, {"rank": 42, "score": 12, "rating": 2178, "username": "Patolindo", "title": "NM", "performance": 2449}, {"rank": 43, "score": 12, "rating": 2179, "username": "marci0107", "performance": 2095}, {"rank": 44, "score": 12, "rating": 2153, "username": "miigaik", "flair": "symbols.peace-symbol", "performance": 2029}, {"rank": 45, "score": 11, "rating": 2280, "username": "magdanoz", "performance": 2563}, {"rank": 46, "score": 11, "rating": 2313, "username": "nikolaylichess", "performance": 2335}, {"rank": 47, "score": 10, "rating": 2347, "username": "ViktorDmitrenko", "title": "IM", "performance": 2226}, {"rank": 48, "score": 10, "rating": 2289, "username": "darkoivankovic1970", "performance": 2100}, {"rank": 49, "score": 10, "rating": 2164, "username": "eugmind", "performance": 2052}, {"rank": 50, "score": 9, "rating": 2245, "username": "EliseevVadim", "performance": 2382}, {"rank": 51, "score": 9, "rating": 2326, "username": "Masterclass2", "title": "FM", "performance": 2233}, {"rank": 52, "score": 9, "rating": 2201, "username": "nanomachine", "performance": 2120}, {"rank": 53, "score": 8, "rating": 2601, "username": "opperwezen", "title": "IM", "flair": "activity.lichess-variant-crazyhouse", "patronColor": 10, "performance": 2745}, {"rank": 54, "score": 8, "rating": 2228, "username": "Maat39", "performance": 2426}, {"rank": 55, "score": 8, "rating": 2336, "username": "Zuykovav", "performance": 2275}, {"rank": 56, "score": 8, "rating": 2231, "username": "Lavi12", "performance": 2185}, {"rank": 57, "score": 8, "rating": 2002, "username": "akhairat", "title": "CM", "performance": 2090}, {"rank": 58, "score": 8, "rating": 2142, "username": "oberschlumpf", "title": "NM", "flair": "nature.dove", "patronColor": 10, "performance": 2025}, {"rank": 59, "score": 7, "rating": 2222, "username": "Marubdob", "performance": 2380}, {"rank": 60, "score": 6, "rating": 2265, "username": "newgamer22", "performance": 2433}, {"rank": 61, "score": 6, "rating": 2219, "username": "MaximChase", "performance": 2085}, {"rank": 62, "score": 5, "rating": 2315, "username": "Greatful", "performance": 2465}, {"rank": 63, "score": 5, "rating": 2298, "username": "notyetgm", "performance": 2137}, {"rank": 64, "score": 5, "rating": 1887, "username": "VLABOR64B", "title": "FM", "performance": 2054}, {"rank": 65, "score": 4, "rating": 2355, "username": "dolynachess", "flair": "symbols.plus", "patronColor": 3, "performance": 2758}, {"rank": 66, "score": 4, "rating": 2323, "username": "laguun", "title": "FM", "flair": "activity.flying-disc", "patronColor": 10, "performance": 2496}, {"rank": 67, "score": 4, "rating": 2334, "username": "adka", "performance": 2350}, {"rank": 68, "score": 4, "rating": 2220, "username": "Holivela", "performance": 2275}, {"rank": 69, "score": 4, "rating": 2275, "username": "Popopuiyt", "title": "FM", "performance": 2262}, {"rank": 70, "score": 4, "rating": 2221, "username": "tsakos27", "title": "FM", "performance": 2248}, {"rank": 71, "score": 4, "rating": 2175, "username": "MonsieurPatate", "performance": 1992}, {"rank": 72, "score": 4, "rating": 2168, "username": "Dobrynia2835", "performance": 1975}, {"rank": 73, "score": 4, "rating": 2132, "username": "Road-To-TheDream", "performance": 1889}, {"rank": 74, "score": 3, "rating": 2453, "username": "Danirod", "title": "FM", "performance": 2485}, {"rank": 75, "score": 3, "rating": 2342, "username": "DA4i2i0", "performance": 2247}, {"rank": 76, "score": 3, "rating": 2279, "username": "eldaruralsk", "performance": 2163}, {"rank": 77, "score": 3, "rating": 2234, "username": "flamaster7", "title": "NM", "performance": 2115}, {"rank": 78, "score": 2, "rating": 2617, "username": "Wolverines1", "title": "GM", "performance": 2737}, {"rank": 79, "score": 2, "rating": 2283, "username": "ManofForest", "performance": 2310}, {"rank": 80, "score": 2, "rating": 2325, "username": "HokutoNoKen7", "title": "FM", "performance": 2243}, {"rank": 81, "score": 2, "rating": 2218, "username": "mkid", "performance": 2176}, {"rank": 82, "score": 2, "rating": 2139, "username": "oskrard", "performance": 2082}, {"rank": 83, "score": 2, "rating": 2240, "username": "Raen2005", "flair": "nature.elephant", "performance": 2011}, {"rank": 84, "score": 2, "rating": 2208, "username": "Chess2120", "performance": 2001}, {"rank": 85, "score": 1, "rating": 2143, "username": "aa80", "performance": 1817}, {"rank": 86, "score": 0, "rating": 2582, "username": "Gullfaksi", "performance": 0}, {"rank": 87, "score": 0, "rating": 2223, "username": "shahrokhameri", "performance": 0}, {"rank": 88, "score": 0, "rating": 2205, "username": "VotaryChess", "performance": 0}, {"rank": 89, "score": 0, "rating": 2202, "username": "goldenrule", "performance": 0}, {"rank": 90, "score": 0, "rating": 2111, "username": "Distinctive", "performance": 0}, {"rank": 91, "score": 0, "rating": 2078, "username": "Rickyrich", "title": "NM", "flair": "activity.lichess-mohawk", "performance": 0}, {"rank": 92, "score": 0, "rating": 2284, "username": "Yasha37", "title": "IM", "performance": 1899}, {"rank": 93, "score": 0, "rating": 2317, "username": "Gorostovsky", "performance": 1836}, {"rank": 94, "score": 0, "rating": 2368, "username": "alikkimron", "performance": 1833}, {"rank": 95, "score": 0, "rating": 2225, "username": "libullet", "performance": 1825}, {"rank": 96, "score": 0, "rating": 2366, "username": "tom230", "performance": 1812}, {"rank": 97, "score": 0, "rating": 2330, "username": "mcdeniss", "performance": 1795}, {"rank": 98, "score": 0, "rating": 2193, "username": "ketua_umum", "performance": 1781}, {"rank": 99, "score": 0, "rating": 2242, "username": "Rital44", "performance": 1778}, {"rank": 100, "score": 0, "rating": 2197, "username": "mamina_tetka", "performance": 1759}, {"rank": 101, "score": 0, "rating": 2186, "username": "NightKing3", "performance": 1751}, {"rank": 102, "score": 0, "rating": 2151, "username": "Pavel2835", "performance": 1711}, {"rank": 103, "score": 0, "rating": 1942, "username": "colinov", "title": "CM", "performance": 1678}, {"rank": 104, "score": 0, "rating": 2178, "username": "k5lineals", "performance": 1677}, {"rank": 105, "score": 0, "rating": 2217, "username": "batuhannozen", "title": "CM", "performance": 1657}, {"rank": 106, "score": 0, "rating": 2200, "username": "ChessPatzerFrance", "performance": 1644}], "longest_game_moves": 212, "biggest_upset": {"diff": 381, "winner": "HrvojeZagreb", "loser": "Meldney"}, "player_stats": {"oberschlumpf": {"games": 9, "wins": 3, "moves": 401, "berserks": 0, "best_streak": 3}, "Niper13": {"games": 16, "wins": 8, "moves": 672, "berserks": 14, "best_streak": 4}, "oldmisio": {"games": 13, "wins": 6, "moves": 462, "berserks": 0, "best_streak": 5}, "SunoftheBeach": {"games": 23, "wins": 13, "moves": 902, "berserks": 0, "best_streak": 6}, "fatalispm": {"games": 18, "wins": 13, "moves": 691, "berserks": 9, "best_streak": 9}, "Belsazar": {"games": 14, "wins": 6, "moves": 560, "berserks": 0, "best_streak": 2}, "smashinglad": {"games": 19, "wins": 8, "moves": 884, "berserks": 1, "best_streak": 3}, "uhlmannfan": {"games": 9, "wins": 6, "moves": 362, "berserks": 0, "best_streak": 4}, "PchelkinVK": {"games": 25, "wins": 16, "moves": 933, "berserks": 6, "best_streak": 3}, "Zairona": {"games": 24, "wins": 9, "moves": 1047, "berserks": 0, "best_streak": 2}, "berto777": {"games": 13, "wins": 5, "moves": 469, "berserks": 0, "best_streak": 3}, "Patolindo": {"games": 7, "wins": 5, "moves": 242, "berserks": 0, "best_streak": 3}, "TausendjahrigeAdler": {"games": 22, "wins": 12, "moves": 903, "berserks": 0, "best_streak": 3}, "HrvojeZagreb": {"games": 20, "wins": 9, "moves": 945, "berserks": 0, "best_streak": 3}, "StepanOsinovsky": {"games": 20, "wins": 10, "moves": 884, "berserks": 0, "best_streak": 2}, "tapkus": {"games": 15, "wins": 8, "moves": 572, "berserks": 0, "best_streak": 3}, "sapber": {"games": 21, "wins": 11, "moves": 830, "berserks": 1, "best_streak": 3}, "Shilichkov": {"games": 9, "wins": 7, "moves": 450, "berserks": 2, "best_streak": 4}, "PJatoba": {"games": 15, "wins": 9, "moves": 618, "berserks": 0, "best_streak": 4}, "Kinzya1": {"games": 20, "wins": 12, "moves": 954, "berserks": 0, "best_streak": 6}, "Strelok2222": {"games": 25, "wins": 12, "moves": 1031, "berserks": 9, "best_streak": 2}, "DOOGE228": {"games": 24, "wins": 13, "moves": 1005, "berserks": 0, "best_streak": 4}, "Gagik-navak": {"games": 24, "wins": 9, "moves": 922, "berserks": 0, "best_streak": 3}, "Grammnik": {"games": 10, "wins": 7, "moves": 374, "berserks": 0, "best_streak": 3}, "miigaik": {"games": 22, "wins": 5, "moves": 875, "berserks": 0, "best_streak": 1}, "akhairat": {"games": 12, "wins": 4, "moves": 444, "berserks": 3, "best_streak": 2}, "papasi": {"games": 26, "wins": 18, "moves": 974, "berserks": 2, "best_streak": 5}, "Greatful": {"games": 3, "wins": 2, "moves": 118, "berserks": 0, "best_streak": 2}, "Damianlamy": {"games": 24, "wins": 11, "moves": 1053, "berserks": 3, "best_streak": 5}, "adrinalin": {"games": 13, "wins": 6, "moves": 665, "berserks": 0, "best_streak": 2}, "Dobrynia2835": {"games": 10, "wins": 2, "moves": 349, "berserks": 0, "best_streak": 1}, "VLABOR64B": {"games": 7, "wins": 2, "moves": 281, "berserks": 4, "best_streak": 1}, "DrGodstein": {"games": 19, "wins": 9, "moves": 886, "berserks": 0, "best_streak": 4}, "opperwezen": {"games": 3, "wins": 3, "moves": 68, "berserks": 0, "best_streak": 3}, "eugmind": {"games": 15, "wins": 4, "moves": 504, "berserks": 6, "best_streak": 2}, "Loay23": {"games": 19, "wins": 12, "moves": 874, "berserks": 0, "best_streak": 7}, "Rital44": {"games": 1, "wins": 0, "moves": 66, "berserks": 0, "best_streak": 0}, "Grandi66": {"games": 18, "wins": 9, "moves": 911, "berserks": 0, "best_streak": 2}, "gefuehlter_FM": {"games": 6, "wins": 5, "moves": 241, "berserks": 0, "best_streak": 5}, "MonsieurPatate": {"games": 7, "wins": 2, "moves": 301, "berserks": 0, "best_streak": 1}, "Coup_de_Grace": {"games": 15, "wins": 8, "moves": 812, "berserks": 0, "best_streak": 3}, "Meldney": {"games": 14, "wins": 9, "moves": 739, "berserks": 0, "best_streak": 4}, "ShaSerOl": {"games": 17, "wins": 5, "moves": 655, "berserks": 0, "best_streak": 4}, "jigsaw123": {"games": 15, "wins": 5, "moves": 678, "berserks": 4, "best_streak": 3}, "k5lineals": {"games": 2, "wins": 0, "moves": 86, "berserks": 0, "best_streak": 0}, "mkid": {"games": 2, "wins": 1, "moves": 49, "berserks": 0, "best_streak": 1}, "Chaozu": {"games": 14, "wins": 8, "moves": 542, "berserks": 0, "best_streak": 5}, "Zuykovav": {"games": 6, "wins": 3, "moves": 241, "berserks": 0, "best_streak": 3}, "zakramnika": {"games": 15, "wins": 9, "moves": 559, "berserks": 2, "best_streak": 4}, "batuhannozen": {"games": 1, "wins": 0, "moves": 74, "berserks": 0, "best_streak": 0}, "Wolverines1": {"games": 1, "wins": 1, "moves": 43, "berserks": 0, "best_streak": 1}, "Pavel2835": {"games": 9, "wins": 0, "moves": 218, "berserks": 0, "best_streak": 0}, "jesselroy99": {"games": 6, "wins": 4, "moves": 213, "berserks": 0, "best_streak": 4}, "Sergey_Naboka": {"games": 10, "wins": 7, "moves": 516, "berserks": 2, "best_streak": 4}, "Win-all-you": {"games": 15, "wins": 7, "moves": 596, "berserks": 0, "best_streak": 4}, "nanomachine": {"games": 12, "wins": 4, "moves": 451, "berserks": 0, "best_streak": 2}, "marci0107": {"games": 14, "wins": 4, "moves": 525, "berserks": 0, "best_streak": 3}, "colinov": {"games": 2, "wins": 0, "moves": 94, "berserks": 0, "best_streak": 0}, "newgamer22": {"games": 3, "wins": 2, "moves": 124, "berserks": 3, "best_streak": 2}, "Chess2120": {"games": 5, "wins": 1, "moves": 163, "berserks": 0, "best_streak": 1}, "Masterclass2": {"games": 8, "wins": 3, "moves": 425, "berserks": 2, "best_streak": 2}, "JorgeHerreraQuintero": {"games": 10, "wins": 7, "moves": 541, "berserks": 3, "best_streak": 3}, "Road-To-TheDream": {"games": 14, "wins": 2, "moves": 530, "berserks": 0, "best_streak": 1}, "nikolaylichess": {"games": 11, "wins": 5, "moves": 634, "berserks": 0, "best_streak": 2}, "eldaruralsk": {"games": 3, "wins": 1, "moves": 106, "berserks": 0, "best_streak": 1}, "ExtremeTactic": {"games": 12, "wins": 7, "moves": 551, "berserks": 0, "best_streak": 3}, "Holivela": {"games": 4, "wins": 2, "moves": 185, "berserks": 0, "best_streak": 2}, "Popopuiyt": {"games": 4, "wins": 2, "moves": 178, "berserks": 0, "best_streak": 2}, "magdanoz": {"games": 6, "wins": 4, "moves": 432, "berserks": 0, "best_streak": 3}, "darkoivankovic1970": {"games": 13, "wins": 4, "moves": 533, "berserks": 0, "best_streak": 3}, "libullet": {"games": 1, "wins": 0, "moves": 22, "berserks": 0, "best_streak": 0}, "ViktorDmitrenko": {"games": 10, "wins": 4, "moves": 313, "berserks": 0, "best_streak": 2}, "Maat39": {"games": 5, "wins": 3, "moves": 206, "berserks": 0, "best_streak": 3}, "Pliukha_M": {"games": 7, "wins": 4, "moves": 372, "berserks": 0, "best_streak": 4}, "DA4i2i0": {"games": 3, "wins": 1, "moves": 202, "berserks": 0, "best_streak": 1}, "ChessPatzerFrance": {"games": 1, "wins": 0, "moves": 53, "berserks": 0, "best_streak": 0}, "dolynachess": {"games": 2, "wins": 2, "moves": 84, "berserks": 0, "best_streak": 2}, "ManofForest": {"games": 2, "wins": 1, "moves": 124, "berserks": 0, "best_streak": 1}, "Lavi12": {"games": 8, "wins": 3, "moves": 378, "berserks": 0, "best_streak": 2}, "MaximChase": {"games": 8, "wins": 3, "moves": 282, "berserks": 0, "best_streak": 1}, "EliseevVadim": {"games": 8, "wins": 4, "moves": 463, "berserks": 0, "best_streak": 2}, "Gorostovsky": {"games": 1, "wins": 0, "moves": 86, "berserks": 1, "best_streak": 0}, "aa80": {"games": 8, "wins": 0, "moves": 341, "berserks": 0, "best_streak": 0}, "ketua_umum": {"games": 3, "wins": 0, "moves": 115, "berserks": 0, "best_streak": 0}, "notyetgm": {"games": 8, "wins": 2, "moves": 343, "berserks": 0, "best_streak": 1}, "laguun": {"games": 3, "wins": 2, "moves": 149, "berserks": 0, "best_streak": 2}, "alikkimron": {"games": 1, "wins": 0, "moves": 51, "berserks": 1, "best_streak": 0}, "Yasha37": {"games": 1, "wins": 0, "moves": 63, "berserks": 0, "best_streak": 0}, "NightKing3": {"games": 5, "wins": 0, "moves": 202, "berserks": 0, "best_streak": 0}, "HokutoNoKen7": {"games": 2, "wins": 1, "moves": 58, "berserks": 0, "best_streak": 1}, "adka": {"games": 4, "wins": 2, "moves": 137, "berserks": 0, "best_streak": 2}, "Raen2005": {"games": 4, "wins": 1, "moves": 57, "berserks": 0, "best_streak": 1}, "tsakos27": {"games": 4, "wins": 1, "moves": 179, "berserks": 0, "best_streak": 1}, "Marubdob": {"games": 4, "wins": 2, "moves": 220, "berserks": 2, "best_streak": 2}, "Danirod": {"games": 2, "wins": 1, "moves": 138, "berserks": 0, "best_streak": 1}, "flamaster7": {"games": 4, "wins": 1, "moves": 127, "berserks": 1, "best_streak": 1}, "tom230": {"games": 1, "wins": 0, "moves": 55, "berserks": 0, "best_streak": 0}, "oskrard": {"games": 3, "wins": 0, "moves": 132, "berserks": 0, "best_streak": 0}, "mamina_tetka": {"games": 1, "wins": 0, "moves": 55, "berserks": 0, "best_streak": 0}, "mcdeniss": {"games": 1, "wins": 0, "moves": 31, "berserks": 0, "best_streak": 0}}}